dztimer/dztimer_ext.pypy38-pp73-x86_64-linux-gnu.so
dztimer/__init__.py
dztimer-1.1.1.dist-info/WHEEL
dztimer-1.1.1.dist-info/RECORD
dztimer-1.1.1.dist-info/METADATA
dztimer-1.1.1.dist-info/licenses/LICENSE
