Metadata-Version: 2.1
Name: dztimer
Version: 1.1.1
Summary: A beautiful timer from ufomap by Daniel Duberg, nanobind by Qingwen Zhang
Author-Email: Qingwen Zhang <qzhangcb@connect.ust.hk>, Daniel Duberg <dduberg@kth.se>
Classifier: License :: OSI Approved :: BSD License
Classifier: Programming Language :: Python :: 3
Classifier: Programming Language :: Python :: 3.8
Classifier: Programming Language :: Python :: 3.9
Classifier: Programming Language :: Python :: 3.10
Classifier: Programming Language :: Python :: 3.11
Classifier: Programming Language :: Python :: 3.12
Project-URL: Homepage, https://github.com/KTH-RPL/dztimer
Requires-Python: >=3.8
